rayshnakht/__init__.py
rayshnakht/rayshnakht_v1.py
rayshnakht-0.1.0.dist-info/LICENSE
rayshnakht-0.1.0.dist-info/METADATA
rayshnakht-0.1.0.dist-info/WHEEL
rayshnakht-0.1.0.dist-info/top_level.txt
rayshnakht-0.1.0.dist-info/RECORD
