Metadata-Version: 2.1
Name: rayshnakht
Version: 0.1.0
Summary: A custom hashing algorithm
Home-page: https://github.com/yourusername/rayshnakht
Author: Patnutsh
Author-email: patnutsh@proton.me
Classifier: Programming Language :: Python :: 3
Classifier: License :: OSI Approved :: MIT License
Classifier: Operating System :: OS Independent
Requires-Python: >=3.6
License-File: LICENSE
